README.md
setup.cfg
setup.py
mcfw/__init__.py
mcfw/cache.py
mcfw/consts.py
mcfw/exceptions.py
mcfw/properties.py
mcfw/restapi.py
mcfw/rpc.py
mcfw/serialization.py
mcfw.egg-info/PKG-INFO
mcfw.egg-info/SOURCES.txt
mcfw.egg-info/dependency_links.txt
mcfw.egg-info/pbr.json
mcfw.egg-info/top_level.txt
test/test.py