Metadata-Version: 1.1
Name: mcfw
Version: 0.3.1
Summary: Framework for easy caching and rest api calls in google appengine projects
Home-page: https://github.com/rogerthat-platform/mcfw
Author: Green IT Globe
Author-email: apps@greenitglobe.com
License: Apache 2.0
Keywords: mcfw,appengine,rest,cache
Platform: UNKNOWN
Classifier: Programming Language :: Python :: 2.7
Classifier: Environment :: Web Environment
Classifier: Operating System :: OS Independent
Classifier: Programming Language :: Python
Classifier: Topic :: Software Development :: Libraries
Classifier: Development Status :: 5 - Production/Stable
Classifier: Intended Audience :: Developers
Classifier: License :: OSI Approved :: Apache Software License
